odoo/addons/account_move_fiscal_year/README.rst
odoo/addons/account_move_fiscal_year/__init__.py
odoo/addons/account_move_fiscal_year/__manifest__.py
odoo/addons/account_move_fiscal_year/i18n/account_move_fiscal_year.pot
odoo/addons/account_move_fiscal_year/i18n/am.po
odoo/addons/account_move_fiscal_year/i18n/ar.po
odoo/addons/account_move_fiscal_year/i18n/ca.po
odoo/addons/account_move_fiscal_year/i18n/de.po
odoo/addons/account_move_fiscal_year/i18n/es.po
odoo/addons/account_move_fiscal_year/i18n/es_CO.po
odoo/addons/account_move_fiscal_year/i18n/es_EC.po
odoo/addons/account_move_fiscal_year/i18n/fr.po
odoo/addons/account_move_fiscal_year/i18n/fr_FR.po
odoo/addons/account_move_fiscal_year/i18n/gl.po
odoo/addons/account_move_fiscal_year/i18n/hr.po
odoo/addons/account_move_fiscal_year/i18n/hr_HR.po
odoo/addons/account_move_fiscal_year/i18n/it.po
odoo/addons/account_move_fiscal_year/i18n/nl.po
odoo/addons/account_move_fiscal_year/i18n/pt.po
odoo/addons/account_move_fiscal_year/i18n/pt_BR.po
odoo/addons/account_move_fiscal_year/i18n/pt_PT.po
odoo/addons/account_move_fiscal_year/i18n/sl.po
odoo/addons/account_move_fiscal_year/i18n/tr_TR.po
odoo/addons/account_move_fiscal_year/models/__init__.py
odoo/addons/account_move_fiscal_year/models/account_move.py
odoo/addons/account_move_fiscal_year/models/account_move_line.py
odoo/addons/account_move_fiscal_year/static/description/icon.png
odoo/addons/account_move_fiscal_year/tests/__init__.py
odoo/addons/account_move_fiscal_year/tests/test_account_move_fiscal_year.py
odoo/addons/account_move_fiscal_year/views/account_move.xml
odoo/addons/account_move_fiscal_year/views/account_move_line.xml
odoo11_addon_account_move_fiscal_year-11.0.1.1.0.dist-info/METADATA
odoo11_addon_account_move_fiscal_year-11.0.1.1.0.dist-info/WHEEL
odoo11_addon_account_move_fiscal_year-11.0.1.1.0.dist-info/top_level.txt
odoo11_addon_account_move_fiscal_year-11.0.1.1.0.dist-info/RECORD
